aws_jupyter_proxy/__init__.py
aws_jupyter_proxy/awsconfig.py
aws_jupyter_proxy/awsproxy.py
aws_jupyter_proxy/handlers.py
aws_jupyter_proxy/etc/aws_jupyter_proxy.json
aws_jupyter_proxy-0.3.7.data/data/etc/jupyter/jupyter_notebook_config.d/aws_jupyter_proxy.json
tests/__init__.py
tests/unit/__init__.py
tests/unit/test_awsconfig.py
tests/unit/test_awsproxy.py
tests/unit/test_handlers.py
aws_jupyter_proxy-0.3.7.dist-info/LICENSE
aws_jupyter_proxy-0.3.7.dist-info/METADATA
aws_jupyter_proxy-0.3.7.dist-info/NOTICE
aws_jupyter_proxy-0.3.7.dist-info/WHEEL
aws_jupyter_proxy-0.3.7.dist-info/top_level.txt
aws_jupyter_proxy-0.3.7.dist-info/RECORD
